{
  "id": "mapproxy_1000",
  "url": "https://giscache.co.clatsop.or.us/county-aerials/wms",
  "visibility": false,
  "visibleLayers": [
    "naip2020"
  ],
  "opacity": 1,
  "title": "County Aerial Photos",
  "itemId": "08d7a28708f7426c966872bb9efeb75d",
  "version": "1.3.0",
  "mapUrl": "https://giscache.co.clatsop.or.us/county-aerials/wms",
  "featureInfoUrl": "https://giscache.co.clatsop.or.us/county-aerials/wms",
  "featureInfoFormat": "text/html",
  "layers": [
    {
      "name": "naip1995",
      "title": "NAIP 1995 1m BW DOQ"
    },
    {
      "name": "naip2000",
      "title": "NAIP 2000 1m BW DOQ"
    },
    {
      "name": "naip2009",
      "title": "NAIP 2009 1/2m 3-band"
    },
    {
      "name": "naip2014",
      "title": "NAIP 2014 1m 4-band"
    },
    {
      "name": "naip2016",
      "title": "NAIP 2016 1m 4-band"
    },
    {
      "name": "osip2018",
      "title": "OSIP 2018 1 foot"
    },
    {
      "name": "naip2020",
      "title": "NAIP 2020 2 foot"
    }
  ],
  "spatialReferences": [
    3857,
    4326,
    4258,
    900913
  ],
  "extent": [
    [
      -124.1,
      45.77
    ],
    [
      -123.35,
      46.3
    ]
  ],
  "maxWidth": 4000,
  "maxHeight": 4000,
  "type": "WMS",
  "layerType": "WMS"
}